<?xml version="1.0" encoding="UTF-8"?>
<Recibos fechaPadron="4T 2025" totalPadron="46395.85" numeroTotalRecibos="77">
  <Recibo idRecibo="0">
    <Exencion>N</Exencion>
    <idFilaExcel>36</idFilaExcel>
    <nombre>Tomás</nombre>
    <primerApellido>Cedron</primerApellido>
    <segundoApellido>Pérez</segundoApellido>
    <NIF>95236547X</NIF>
    <IBAN>DE9221508149195421311111</IBAN>
    <kgGenerados>10</kgGenerados>
    <baseImponibleRecibo>57.75</baseImponibleRecibo>
    <ivaRecibo>8.38</ivaRecibo>
    <totalRecibo>66.13</totalRecibo>
  </Recibo>
  <Recibo idRecibo="1">
    <Exencion>N</Exencion>
    <idFilaExcel>37</idFilaExcel>
    <nombre>Clotilde</nombre>
    <primerApellido>Castro</primerApellido>
    <segundoApellido>Presa</segundoApellido>
    <NIF>15975328B</NIF>
    <IBAN>DE5221346154523164911111</IBAN>
    <kgGenerados>50</kgGenerados>
    <baseImponibleRecibo>187.0</baseImponibleRecibo>
    <ivaRecibo>33.16</ivaRecibo>
    <totalRecibo>220.16</totalRecibo>
  </Recibo>
  <Recibo idRecibo="2">
    <Exencion>N</Exencion>
    <idFilaExcel>39</idFilaExcel>
    <nombre>Sara</nombre>
    <primerApellido>Flórez</primerApellido>
    <segundoApellido>Prieto</segundoApellido>
    <NIF>X7523694A</NIF>
    <IBAN>ES8523164897682213011111</IBAN>
    <kgGenerados>500</kgGenerados>
    <baseImponibleRecibo>11077.0</baseImponibleRecibo>
    <ivaRecibo>2211.16</ivaRecibo>
    <totalRecibo>13288.16</totalRecibo>
  </Recibo>
  <Recibo idRecibo="3">
    <Exencion>N</Exencion>
    <idFilaExcel>40</idFilaExcel>
    <nombre>Encarnación</nombre>
    <primerApellido>López</primerApellido>
    <segundoApellido>Riverto</segundoApellido>
    <NIF>Y2563248G</NIF>
    <IBAN>ES4796536214855214511111</IBAN>
    <kgGenerados>120</kgGenerados>
    <baseImponibleRecibo>1397.0</baseImponibleRecibo>
    <ivaRecibo>275.16</ivaRecibo>
    <totalRecibo>1672.16</totalRecibo>
  </Recibo>
  <Recibo idRecibo="4">
    <Exencion>N</Exencion>
    <idFilaExcel>41</idFilaExcel>
    <nombre>Dolores</nombre>
    <primerApellido>López</primerApellido>
    <segundoApellido>Robles</segundoApellido>
    <NIF>09256324C</NIF>
    <IBAN>ES2285461325261978711111</IBAN>
    <kgGenerados>30</kgGenerados>
    <baseImponibleRecibo>55.0</baseImponibleRecibo>
    <ivaRecibo>8.88</ivaRecibo>
    <totalRecibo>63.88</totalRecibo>
  </Recibo>
  <Recibo idRecibo="5">
    <Exencion>N</Exencion>
    <idFilaExcel>42</idFilaExcel>
    <nombre>Herminia</nombre>
    <primerApellido>Almanzar</primerApellido>
    <segundoApellido>Robles</segundoApellido>
    <NIF>09785530L</NIF>
    <IBAN>FI6024587946002003111111</IBAN>
    <kgGenerados>118</kgGenerados>
    <baseImponibleRecibo>1375.0</baseImponibleRecibo>
    <ivaRecibo>270.76</ivaRecibo>
    <totalRecibo>1645.76</totalRecibo>
  </Recibo>
  <Recibo idRecibo="6">
    <Exencion>N</Exencion>
    <idFilaExcel>43</idFilaExcel>
    <nombre>Sonia</nombre>
    <primerApellido>Pisabarro</primerApellido>
    <segundoApellido>Rodríguez</segundoApellido>
    <NIF>71393396Q</NIF>
    <IBAN>ES0420960043053071411111</IBAN>
    <kgGenerados>154</kgGenerados>
    <baseImponibleRecibo>1771.0</baseImponibleRecibo>
    <ivaRecibo>349.96</ivaRecibo>
    <totalRecibo>2120.96</totalRecibo>
  </Recibo>
  <Recibo idRecibo="7">
    <Exencion>N</Exencion>
    <idFilaExcel>44</idFilaExcel>
    <nombre>Generoso</nombre>
    <primerApellido>Pisabarro</primerApellido>
    <segundoApellido>Rodríguez</segundoApellido>
    <NIF>71406027C</NIF>
    <IBAN>ES3620960043022158811111</IBAN>
    <kgGenerados>57</kgGenerados>
    <baseImponibleRecibo>202.4</baseImponibleRecibo>
    <ivaRecibo>36.24</ivaRecibo>
    <totalRecibo>238.64</totalRecibo>
  </Recibo>
  <Recibo idRecibo="8">
    <Exencion>N</Exencion>
    <idFilaExcel>45</idFilaExcel>
    <nombre>Sergio</nombre>
    <primerApellido>Alaiz</primerApellido>
    <segundoApellido>Salas</segundoApellido>
    <NIF>09548451R</NIF>
    <IBAN>ES6521654587925156411111</IBAN>
    <kgGenerados>99</kgGenerados>
    <baseImponibleRecibo>621.5</baseImponibleRecibo>
    <ivaRecibo>120.06</ivaRecibo>
    <totalRecibo>741.56</totalRecibo>
  </Recibo>
  <Recibo idRecibo="9">
    <Exencion>N</Exencion>
    <idFilaExcel>46</idFilaExcel>
    <nombre>Bonifacio</nombre>
    <primerApellido>Fresco</primerApellido>
    <segundoApellido>Sánchez</segundoApellido>
    <NIF>71597570L</NIF>
    <IBAN>ES0851651681931210611111</IBAN>
    <kgGenerados>65</kgGenerados>
    <baseImponibleRecibo>434.5</baseImponibleRecibo>
    <ivaRecibo>82.66</ivaRecibo>
    <totalRecibo>517.16</totalRecibo>
  </Recibo>
  <Recibo idRecibo="10">
    <Exencion>N</Exencion>
    <idFilaExcel>47</idFilaExcel>
    <nombre>Demetrio</nombre>
    <primerApellido>Fernández</primerApellido>
    <segundoApellido>García</segundoApellido>
    <NIF>09611100K</NIF>
    <IBAN>ES4966552211198855311111</IBAN>
    <kgGenerados>94</kgGenerados>
    <baseImponibleRecibo>594.0</baseImponibleRecibo>
    <ivaRecibo>114.56</ivaRecibo>
    <totalRecibo>708.56</totalRecibo>
  </Recibo>
  <Recibo idRecibo="11">
    <Exencion>N</Exencion>
    <idFilaExcel>48</idFilaExcel>
    <nombre>Germán</nombre>
    <primerApellido>Martínez</primerApellido>
    <segundoApellido>García</segundoApellido>
    <NIF>09769669M</NIF>
    <IBAN>GB5120910936563000011111</IBAN>
    <kgGenerados>41</kgGenerados>
    <baseImponibleRecibo>125.4</baseImponibleRecibo>
    <ivaRecibo>21.9</ivaRecibo>
    <totalRecibo>147.3</totalRecibo>
  </Recibo>
  <Recibo idRecibo="12">
    <Exencion>N</Exencion>
    <idFilaExcel>49</idFilaExcel>
    <nombre>Marta</nombre>
    <primerApellido>López</primerApellido>
    <segundoApellido>Getino</segundoApellido>
    <NIF>09548317M</NIF>
    <IBAN>DE0301821135960205511111</IBAN>
    <kgGenerados>192</kgGenerados>
    <baseImponibleRecibo>4301.0</baseImponibleRecibo>
    <ivaRecibo>855.96</ivaRecibo>
    <totalRecibo>5156.96</totalRecibo>
  </Recibo>
  <Recibo idRecibo="13">
    <Exencion>N</Exencion>
    <idFilaExcel>51</idFilaExcel>
    <nombre>Israel</nombre>
    <primerApellido>Amo</primerApellido>
    <segundoApellido>González</segundoApellido>
    <NIF>09758365V</NIF>
    <IBAN>ES7220960043023075711111</IBAN>
    <kgGenerados>157</kgGenerados>
    <baseImponibleRecibo>1353.0</baseImponibleRecibo>
    <ivaRecibo>267.42</ivaRecibo>
    <totalRecibo>1620.42</totalRecibo>
  </Recibo>
  <Recibo idRecibo="14">
    <Exencion>N</Exencion>
    <idFilaExcel>52</idFilaExcel>
    <nombre>Gabriel</nombre>
    <primerApellido>Prieto</primerApellido>
    <segundoApellido>González</segundoApellido>
    <NIF>02614035Q</NIF>
    <IBAN>SM2725635478301002511111</IBAN>
    <kgGenerados>126</kgGenerados>
    <baseImponibleRecibo>1463.0</baseImponibleRecibo>
    <ivaRecibo>288.36</ivaRecibo>
    <totalRecibo>1751.36</totalRecibo>
  </Recibo>
  <Recibo idRecibo="15">
    <Exencion>N</Exencion>
    <idFilaExcel>53</idFilaExcel>
    <nombre>Rubén Darío</nombre>
    <primerApellido>García</primerApellido>
    <segundoApellido>Gracia</segundoApellido>
    <NIF>09570242B</NIF>
    <IBAN>ES1432154697135423111111</IBAN>
    <kgGenerados>184</kgGenerados>
    <baseImponibleRecibo>4125.0</baseImponibleRecibo>
    <ivaRecibo>820.76</ivaRecibo>
    <totalRecibo>4945.76</totalRecibo>
  </Recibo>
  <Recibo idRecibo="16">
    <Exencion>N</Exencion>
    <idFilaExcel>55</idFilaExcel>
    <nombre>Alencar</nombre>
    <primerApellido>Fresco</primerApellido>
    <segundoApellido>Gutierrez</segundoApellido>
    <NIF>09548501M</NIF>
    <IBAN>GB2420008521528775111111</IBAN>
    <kgGenerados>44</kgGenerados>
    <baseImponibleRecibo>173.8</baseImponibleRecibo>
    <ivaRecibo>30.52</ivaRecibo>
    <totalRecibo>204.32</totalRecibo>
  </Recibo>
  <Recibo idRecibo="17">
    <Exencion>N</Exencion>
    <idFilaExcel>176</idFilaExcel>
    <nombre>Tomás</nombre>
    <primerApellido>Pérez</primerApellido>
    <segundoApellido>Cedron</segundoApellido>
    <NIF>71256665C</NIF>
    <IBAN>DE9221508149195421311111</IBAN>
    <kgGenerados>10</kgGenerados>
    <baseImponibleRecibo>18.32</baseImponibleRecibo>
    <ivaRecibo>3.6</ivaRecibo>
    <totalRecibo>21.92</totalRecibo>
  </Recibo>
  <Recibo idRecibo="18">
    <Exencion>N</Exencion>
    <idFilaExcel>177</idFilaExcel>
    <nombre>Clotilde</nombre>
    <primerApellido>Presa</primerApellido>
    <segundoApellido>Castro</segundoApellido>
    <NIF>71256675F</NIF>
    <IBAN>DE1921346154543164911122</IBAN>
    <kgGenerados>50</kgGenerados>
    <baseImponibleRecibo>36.63</baseImponibleRecibo>
    <ivaRecibo>7.19</ivaRecibo>
    <totalRecibo>43.82</totalRecibo>
  </Recibo>
  <Recibo idRecibo="19">
    <Exencion>N</Exencion>
    <idFilaExcel>178</idFilaExcel>
    <nombre>Cristina</nombre>
    <primerApellido>Prieto</primerApellido>
    <segundoApellido>Alonso</segundoApellido>
    <NIF>71256685V</NIF>
    <IBAN>ES1625187786321225411111</IBAN>
    <kgGenerados>141</kgGenerados>
    <baseImponibleRecibo>145.41</baseImponibleRecibo>
    <ivaRecibo>28.56</ivaRecibo>
    <totalRecibo>173.97</totalRecibo>
  </Recibo>
  <Recibo idRecibo="20">
    <Exencion>N</Exencion>
    <idFilaExcel>179</idFilaExcel>
    <nombre>Sara</nombre>
    <primerApellido>Prieto</primerApellido>
    <segundoApellido>Flórez</segundoApellido>
    <NIF>71256695G</NIF>
    <IBAN>ES8523164897682213011111</IBAN>
    <kgGenerados>500</kgGenerados>
    <baseImponibleRecibo>1874.79</baseImponibleRecibo>
    <ivaRecibo>368.2</ivaRecibo>
    <totalRecibo>2242.99</totalRecibo>
  </Recibo>
  <Recibo idRecibo="21">
    <Exencion>N</Exencion>
    <idFilaExcel>180</idFilaExcel>
    <nombre>Encarnación</nombre>
    <primerApellido>Riverto</primerApellido>
    <segundoApellido>López</segundoApellido>
    <NIF>71256705Z</NIF>
    <IBAN>ES4796536214855214511111</IBAN>
    <kgGenerados>120</kgGenerados>
    <baseImponibleRecibo>98.79</baseImponibleRecibo>
    <ivaRecibo>19.4</ivaRecibo>
    <totalRecibo>118.19</totalRecibo>
  </Recibo>
  <Recibo idRecibo="22">
    <Exencion>N</Exencion>
    <idFilaExcel>181</idFilaExcel>
    <nombre>Dolores</nombre>
    <primerApellido>Robles</primerApellido>
    <segundoApellido>López</segundoApellido>
    <NIF>71256715R</NIF>
    <IBAN>ES2285461325261978711111</IBAN>
    <kgGenerados>30</kgGenerados>
    <baseImponibleRecibo>14.99</baseImponibleRecibo>
    <ivaRecibo>2.95</ivaRecibo>
    <totalRecibo>17.94</totalRecibo>
  </Recibo>
  <Recibo idRecibo="23">
    <Exencion>N</Exencion>
    <idFilaExcel>182</idFilaExcel>
    <nombre>Herminia</nombre>
    <primerApellido>Robles</primerApellido>
    <segundoApellido>Almanzar</segundoApellido>
    <NIF>71256725B</NIF>
    <IBAN>FI2724587946022003111122</IBAN>
    <kgGenerados>118</kgGenerados>
    <baseImponibleRecibo>96.57</baseImponibleRecibo>
    <ivaRecibo>18.97</ivaRecibo>
    <totalRecibo>115.54</totalRecibo>
  </Recibo>
  <Recibo idRecibo="24">
    <Exencion>N</Exencion>
    <idFilaExcel>183</idFilaExcel>
    <nombre>Sonia</nombre>
    <primerApellido>Rodríguez</primerApellido>
    <segundoApellido>Pisabarro</segundoApellido>
    <NIF>71256735K</NIF>
    <IBAN>ES0420960043053071411111</IBAN>
    <kgGenerados>154</kgGenerados>
    <baseImponibleRecibo>174.27</baseImponibleRecibo>
    <ivaRecibo>34.23</ivaRecibo>
    <totalRecibo>208.5</totalRecibo>
  </Recibo>
  <Recibo idRecibo="25">
    <Exencion>N</Exencion>
    <idFilaExcel>184</idFilaExcel>
    <nombre>Generoso</nombre>
    <primerApellido>Rodríguez</primerApellido>
    <segundoApellido>Pisabarro</segundoApellido>
    <NIF>71256745P</NIF>
    <IBAN>ES3620960043022158811111</IBAN>
    <kgGenerados>57</kgGenerados>
    <baseImponibleRecibo>38.96</baseImponibleRecibo>
    <ivaRecibo>7.65</ivaRecibo>
    <totalRecibo>46.61</totalRecibo>
  </Recibo>
  <Recibo idRecibo="26">
    <Exencion>N</Exencion>
    <idFilaExcel>185</idFilaExcel>
    <nombre>Sergio</nombre>
    <primerApellido>Salas</primerApellido>
    <segundoApellido>Alaiz</segundoApellido>
    <NIF>71256755H</NIF>
    <IBAN>ES6521654587925156411111</IBAN>
    <kgGenerados>99</kgGenerados>
    <baseImponibleRecibo>75.48</baseImponibleRecibo>
    <ivaRecibo>14.82</ivaRecibo>
    <totalRecibo>90.3</totalRecibo>
  </Recibo>
  <Recibo idRecibo="27">
    <Exencion>N</Exencion>
    <idFilaExcel>187</idFilaExcel>
    <nombre>Demetrio</nombre>
    <primerApellido>García</primerApellido>
    <segundoApellido>Fernández</segundoApellido>
    <NIF>71256775S</NIF>
    <IBAN>ES4966552211198855311111</IBAN>
    <kgGenerados>94</kgGenerados>
    <baseImponibleRecibo>69.93</baseImponibleRecibo>
    <ivaRecibo>13.73</ivaRecibo>
    <totalRecibo>83.66</totalRecibo>
  </Recibo>
  <Recibo idRecibo="28">
    <Exencion>N</Exencion>
    <idFilaExcel>188</idFilaExcel>
    <nombre>Germán</nombre>
    <primerApellido>García</primerApellido>
    <segundoApellido>Martínez</segundoApellido>
    <NIF>71256785W</NIF>
    <IBAN>GB5120910936563000011111</IBAN>
    <kgGenerados>41</kgGenerados>
    <baseImponibleRecibo>25.23</baseImponibleRecibo>
    <ivaRecibo>4.95</ivaRecibo>
    <totalRecibo>30.18</totalRecibo>
  </Recibo>
  <Recibo idRecibo="29">
    <Exencion>N</Exencion>
    <idFilaExcel>189</idFilaExcel>
    <nombre>Marta</nombre>
    <primerApellido>Getino</primerApellido>
    <segundoApellido>López</segundoApellido>
    <NIF>71256795N</NIF>
    <IBAN>DE0301821135960205511111</IBAN>
    <kgGenerados>192</kgGenerados>
    <baseImponibleRecibo>258.63</baseImponibleRecibo>
    <ivaRecibo>50.79</ivaRecibo>
    <totalRecibo>309.42</totalRecibo>
  </Recibo>
  <Recibo idRecibo="30">
    <Exencion>N</Exencion>
    <idFilaExcel>190</idFilaExcel>
    <nombre>Israel</nombre>
    <primerApellido>Gomara</primerApellido>
    <segundoApellido>Amo</segundoApellido>
    <NIF>71256805E</NIF>
    <IBAN>DE2922631245516916411111</IBAN>
    <kgGenerados>88</kgGenerados>
    <baseImponibleRecibo>63.27</baseImponibleRecibo>
    <ivaRecibo>12.43</ivaRecibo>
    <totalRecibo>75.7</totalRecibo>
  </Recibo>
  <Recibo idRecibo="31">
    <Exencion>N</Exencion>
    <idFilaExcel>191</idFilaExcel>
    <nombre>Israel</nombre>
    <primerApellido>González</primerApellido>
    <segundoApellido>Amo</segundoApellido>
    <NIF>71256815D</NIF>
    <IBAN>ES3920960043043075711122</IBAN>
    <kgGenerados>157</kgGenerados>
    <baseImponibleRecibo>135.7</baseImponibleRecibo>
    <ivaRecibo>26.65</ivaRecibo>
    <totalRecibo>162.35</totalRecibo>
  </Recibo>
  <Recibo idRecibo="32">
    <Exencion>N</Exencion>
    <idFilaExcel>192</idFilaExcel>
    <nombre>Gabriel</nombre>
    <primerApellido>González</primerApellido>
    <segundoApellido>Prieto</segundoApellido>
    <NIF>71256825L</NIF>
    <IBAN>SM2725635478301002511111</IBAN>
    <kgGenerados>126</kgGenerados>
    <baseImponibleRecibo>112.11</baseImponibleRecibo>
    <ivaRecibo>22.02</ivaRecibo>
    <totalRecibo>134.13</totalRecibo>
  </Recibo>
  <Recibo idRecibo="33">
    <Exencion>N</Exencion>
    <idFilaExcel>195</idFilaExcel>
    <nombre>Alencar</nombre>
    <primerApellido>Gutierrez</primerApellido>
    <segundoApellido>Fresco</segundoApellido>
    <NIF>71256855A</NIF>
    <IBAN>GB2420008521528775111111</IBAN>
    <kgGenerados>44</kgGenerados>
    <baseImponibleRecibo>34.63</baseImponibleRecibo>
    <ivaRecibo>6.8</ivaRecibo>
    <totalRecibo>41.43</totalRecibo>
  </Recibo>
  <Recibo idRecibo="34">
    <Exencion>N</Exencion>
    <idFilaExcel>267</idFilaExcel>
    <nombre>Ismael</nombre>
    <primerApellido>Quintanilla</primerApellido>
    <segundoApellido>Vara</segundoApellido>
    <NIF>71257575X</NIF>
    <IBAN>DK9832541112871220011111</IBAN>
    <kgGenerados>95</kgGenerados>
    <baseImponibleRecibo>71.04</baseImponibleRecibo>
    <ivaRecibo>13.95</ivaRecibo>
    <totalRecibo>84.99</totalRecibo>
  </Recibo>
  <Recibo idRecibo="35">
    <Exencion>N</Exencion>
    <idFilaExcel>268</idFilaExcel>
    <nombre>Diana</nombre>
    <primerApellido>Vega</primerApellido>
    <segundoApellido>Martínes</segundoApellido>
    <NIF>71257585C</NIF>
    <IBAN>LT8562541122401110111188</IBAN>
    <kgGenerados>195</kgGenerados>
    <baseImponibleRecibo>265.29</baseImponibleRecibo>
    <ivaRecibo>52.1</ivaRecibo>
    <totalRecibo>317.39</totalRecibo>
  </Recibo>
  <Recibo idRecibo="36">
    <Exencion>N</Exencion>
    <idFilaExcel>269</idFilaExcel>
    <nombre>Elisa</nombre>
    <primerApellido>Portugues</primerApellido>
    <segundoApellido>Bernal</segundoApellido>
    <NIF>71257595F</NIF>
    <IBAN>ES3555065688721051011111</IBAN>
    <kgGenerados>117</kgGenerados>
    <baseImponibleRecibo>95.46</baseImponibleRecibo>
    <ivaRecibo>18.75</ivaRecibo>
    <totalRecibo>114.21</totalRecibo>
  </Recibo>
  <Recibo idRecibo="37">
    <Exencion>N</Exencion>
    <idFilaExcel>271</idFilaExcel>
    <nombre>Marisa</nombre>
    <primerApellido>Rey</primerApellido>
    <segundoApellido>Sutil</segundoApellido>
    <NIF>71257615G</NIF>
    <IBAN>ES2612548521558742111111</IBAN>
    <kgGenerados>54</kgGenerados>
    <baseImponibleRecibo>37.96</baseImponibleRecibo>
    <ivaRecibo>7.45</ivaRecibo>
    <totalRecibo>45.41</totalRecibo>
  </Recibo>
  <Recibo idRecibo="38">
    <Exencion>S</Exencion>
    <idFilaExcel>272</idFilaExcel>
    <nombre>Marta</nombre>
    <primerApellido>Martinez</primerApellido>
    <segundoApellido>Díez</segundoApellido>
    <NIF>71257625Z</NIF>
    <IBAN>ES2801826530150201511111</IBAN>
    <kgGenerados>76</kgGenerados>
    <baseImponibleRecibo>0.0</baseImponibleRecibo>
    <ivaRecibo>0.0</ivaRecibo>
    <totalRecibo>0.0</totalRecibo>
  </Recibo>
  <Recibo idRecibo="39">
    <Exencion>N</Exencion>
    <idFilaExcel>273</idFilaExcel>
    <nombre>Miguel</nombre>
    <primerApellido>García</primerApellido>
    <segundoApellido>Fernández</segundoApellido>
    <NIF>71257635R</NIF>
    <IBAN>ES1221651651852511111188</IBAN>
    <kgGenerados>67</kgGenerados>
    <baseImponibleRecibo>42.29</baseImponibleRecibo>
    <ivaRecibo>8.3</ivaRecibo>
    <totalRecibo>50.59</totalRecibo>
  </Recibo>
  <Recibo idRecibo="40">
    <Exencion>N</Exencion>
    <idFilaExcel>274</idFilaExcel>
    <nombre>Cruz</nombre>
    <primerApellido>Moncada</primerApellido>
    <segundoApellido>De la fuente</segundoApellido>
    <NIF>71257645B</NIF>
    <IBAN>ES2751651487980005111111</IBAN>
    <kgGenerados>110</kgGenerados>
    <baseImponibleRecibo>65.77</baseImponibleRecibo>
    <ivaRecibo>12.91</ivaRecibo>
    <totalRecibo>78.68</totalRecibo>
  </Recibo>
  <Recibo idRecibo="41">
    <Exencion>N</Exencion>
    <idFilaExcel>276</idFilaExcel>
    <nombre>Hugo</nombre>
    <primerApellido>Lombás</primerApellido>
    <segundoApellido>Pérez</segundoApellido>
    <NIF>71257665P</NIF>
    <IBAN>AT8222515651995640011111</IBAN>
    <kgGenerados>17</kgGenerados>
    <baseImponibleRecibo>25.97</baseImponibleRecibo>
    <ivaRecibo>5.1</ivaRecibo>
    <totalRecibo>31.07</totalRecibo>
  </Recibo>
  <Recibo idRecibo="42">
    <Exencion>N</Exencion>
    <idFilaExcel>325</idFilaExcel>
    <nombre>Cedron</nombre>
    <primerApellido>Tomás</primerApellido>
    <segundoApellido>Pérez</segundoApellido>
    <NIF>71258155S</NIF>
    <IBAN>DE9221508149195421311111</IBAN>
    <kgGenerados>10</kgGenerados>
    <baseImponibleRecibo>46.13</baseImponibleRecibo>
    <ivaRecibo>4.81</ivaRecibo>
    <totalRecibo>50.94</totalRecibo>
  </Recibo>
  <Recibo idRecibo="43">
    <Exencion>N</Exencion>
    <idFilaExcel>326</idFilaExcel>
    <nombre>Castro</nombre>
    <primerApellido>Clotilde</primerApellido>
    <segundoApellido>Presa</segundoApellido>
    <NIF>71258165W</NIF>
    <IBAN>DE5221346154523164911111</IBAN>
    <kgGenerados>50</kgGenerados>
    <baseImponibleRecibo>105.5</baseImponibleRecibo>
    <ivaRecibo>15.14</ivaRecibo>
    <totalRecibo>120.64</totalRecibo>
  </Recibo>
  <Recibo idRecibo="44">
    <Exencion>N</Exencion>
    <idFilaExcel>327</idFilaExcel>
    <nombre>Alonso</nombre>
    <primerApellido>Cristina</primerApellido>
    <segundoApellido>Prieto</segundoApellido>
    <NIF>71258175N</NIF>
    <IBAN>ES5425187786311225411155</IBAN>
    <kgGenerados>141</kgGenerados>
    <baseImponibleRecibo>205.6</baseImponibleRecibo>
    <ivaRecibo>34.98</ivaRecibo>
    <totalRecibo>240.58</totalRecibo>
  </Recibo>
  <Recibo idRecibo="45">
    <Exencion>N</Exencion>
    <idFilaExcel>328</idFilaExcel>
    <nombre>Flórez</nombre>
    <primerApellido>Sara</primerApellido>
    <segundoApellido>Prieto</segundoApellido>
    <NIF>71258185E</NIF>
    <IBAN>ES8523164897682213011111</IBAN>
    <kgGenerados>500</kgGenerados>
    <baseImponibleRecibo>600.5</baseImponibleRecibo>
    <ivaRecibo>113.24</ivaRecibo>
    <totalRecibo>713.74</totalRecibo>
  </Recibo>
  <Recibo idRecibo="46">
    <Exencion>N</Exencion>
    <idFilaExcel>329</idFilaExcel>
    <nombre>López</nombre>
    <primerApellido>Encarnación</primerApellido>
    <segundoApellido>Riverto</segundoApellido>
    <NIF>71258195D</NIF>
    <IBAN>ES4796536214855214511111</IBAN>
    <kgGenerados>120</kgGenerados>
    <baseImponibleRecibo>182.5</baseImponibleRecibo>
    <ivaRecibo>30.4</ivaRecibo>
    <totalRecibo>212.9</totalRecibo>
  </Recibo>
  <Recibo idRecibo="47">
    <Exencion>N</Exencion>
    <idFilaExcel>330</idFilaExcel>
    <nombre>López</nombre>
    <primerApellido>Dolores</primerApellido>
    <segundoApellido>Robles</segundoApellido>
    <NIF>71258205L</NIF>
    <IBAN>ES2285461325261978711111</IBAN>
    <kgGenerados>30</kgGenerados>
    <baseImponibleRecibo>41.75</baseImponibleRecibo>
    <ivaRecibo>5.4</ivaRecibo>
    <totalRecibo>47.15</totalRecibo>
  </Recibo>
  <Recibo idRecibo="48">
    <Exencion>N</Exencion>
    <idFilaExcel>331</idFilaExcel>
    <nombre>Almanzar</nombre>
    <primerApellido>Herminia</primerApellido>
    <segundoApellido>Robles</segundoApellido>
    <NIF>71258215Y</NIF>
    <IBAN>FI2524587946082003111155</IBAN>
    <kgGenerados>118</kgGenerados>
    <baseImponibleRecibo>180.3</baseImponibleRecibo>
    <ivaRecibo>29.96</ivaRecibo>
    <totalRecibo>210.26</totalRecibo>
  </Recibo>
  <Recibo idRecibo="49">
    <Exencion>N</Exencion>
    <idFilaExcel>332</idFilaExcel>
    <nombre>Pisabarro</nombre>
    <primerApellido>Sonia</primerApellido>
    <segundoApellido>Rodríguez</segundoApellido>
    <NIF>71258225Q</NIF>
    <IBAN>ES0420960043053071411111</IBAN>
    <kgGenerados>154</kgGenerados>
    <baseImponibleRecibo>219.9</baseImponibleRecibo>
    <ivaRecibo>37.81</ivaRecibo>
    <totalRecibo>257.71</totalRecibo>
  </Recibo>
  <Recibo idRecibo="50">
    <Exencion>N</Exencion>
    <idFilaExcel>333</idFilaExcel>
    <nombre>Pisabarro</nombre>
    <primerApellido>Generoso</primerApellido>
    <segundoApellido>Rodríguez</segundoApellido>
    <NIF>71258235A</NIF>
    <IBAN>ES3620960043022158811111</IBAN>
    <kgGenerados>57</kgGenerados>
    <baseImponibleRecibo>113.2</baseImponibleRecibo>
    <ivaRecibo>16.67</ivaRecibo>
    <totalRecibo>129.87</totalRecibo>
  </Recibo>
  <Recibo idRecibo="51">
    <Exencion>N</Exencion>
    <idFilaExcel>334</idFilaExcel>
    <nombre>Alaiz</nombre>
    <primerApellido>Sergio</primerApellido>
    <segundoApellido>Salas</segundoApellido>
    <NIF>71258245J</NIF>
    <IBAN>ES6521654587925156411111</IBAN>
    <kgGenerados>99</kgGenerados>
    <baseImponibleRecibo>159.4</baseImponibleRecibo>
    <ivaRecibo>25.82</ivaRecibo>
    <totalRecibo>185.22</totalRecibo>
  </Recibo>
  <Recibo idRecibo="52">
    <Exencion>N</Exencion>
    <idFilaExcel>335</idFilaExcel>
    <nombre>Fresco</nombre>
    <primerApellido>Bonifacio</primerApellido>
    <segundoApellido>Sánchez</segundoApellido>
    <NIF>71258255T</NIF>
    <IBAN>ES4051651681921210611166</IBAN>
    <kgGenerados>65</kgGenerados>
    <baseImponibleRecibo>122.0</baseImponibleRecibo>
    <ivaRecibo>18.41</ivaRecibo>
    <totalRecibo>140.41</totalRecibo>
  </Recibo>
  <Recibo idRecibo="53">
    <Exencion>N</Exencion>
    <idFilaExcel>336</idFilaExcel>
    <nombre>Fernández</nombre>
    <primerApellido>Demetrio</primerApellido>
    <segundoApellido>García</segundoApellido>
    <NIF>71258265X</NIF>
    <IBAN>ES4966552211198855311111</IBAN>
    <kgGenerados>94</kgGenerados>
    <baseImponibleRecibo>153.9</baseImponibleRecibo>
    <ivaRecibo>24.73</ivaRecibo>
    <totalRecibo>178.63</totalRecibo>
  </Recibo>
  <Recibo idRecibo="54">
    <Exencion>N</Exencion>
    <idFilaExcel>337</idFilaExcel>
    <nombre>Martínez</nombre>
    <primerApellido>Germán</primerApellido>
    <segundoApellido>García</segundoApellido>
    <NIF>71258275C</NIF>
    <IBAN>GB5120910936563000011111</IBAN>
    <kgGenerados>41</kgGenerados>
    <baseImponibleRecibo>71.7</baseImponibleRecibo>
    <ivaRecibo>9.89</ivaRecibo>
    <totalRecibo>81.59</totalRecibo>
  </Recibo>
  <Recibo idRecibo="55">
    <Exencion>N</Exencion>
    <idFilaExcel>338</idFilaExcel>
    <nombre>López</nombre>
    <primerApellido>Marta</primerApellido>
    <segundoApellido>Getino</segundoApellido>
    <NIF>71258285F</NIF>
    <IBAN>DE0301821135960205511111</IBAN>
    <kgGenerados>192</kgGenerados>
    <baseImponibleRecibo>261.7</baseImponibleRecibo>
    <ivaRecibo>46.1</ivaRecibo>
    <totalRecibo>307.8</totalRecibo>
  </Recibo>
  <Recibo idRecibo="56">
    <Exencion>N</Exencion>
    <idFilaExcel>339</idFilaExcel>
    <nombre>Amo</nombre>
    <primerApellido>Israel</primerApellido>
    <segundoApellido>Gomara</segundoApellido>
    <NIF>71258295V</NIF>
    <IBAN>DE2922631245516916411111</IBAN>
    <kgGenerados>88</kgGenerados>
    <baseImponibleRecibo>147.3</baseImponibleRecibo>
    <ivaRecibo>23.42</ivaRecibo>
    <totalRecibo>170.72</totalRecibo>
  </Recibo>
  <Recibo idRecibo="57">
    <Exencion>N</Exencion>
    <idFilaExcel>340</idFilaExcel>
    <nombre>Amo</nombre>
    <primerApellido>Israel</primerApellido>
    <segundoApellido>González</segundoApellido>
    <NIF>71258305G</NIF>
    <IBAN>ES7220960043023075711111</IBAN>
    <kgGenerados>157</kgGenerados>
    <baseImponibleRecibo>167.4</baseImponibleRecibo>
    <ivaRecibo>28.85</ivaRecibo>
    <totalRecibo>196.25</totalRecibo>
  </Recibo>
  <Recibo idRecibo="58">
    <Exencion>N</Exencion>
    <idFilaExcel>342</idFilaExcel>
    <nombre>García</nombre>
    <primerApellido>Rubén Darío</primerApellido>
    <segundoApellido>Gracia</segundoApellido>
    <NIF>71258325R</NIF>
    <IBAN>ES1432154697135423111111</IBAN>
    <kgGenerados>184</kgGenerados>
    <baseImponibleRecibo>252.9</baseImponibleRecibo>
    <ivaRecibo>44.35</ivaRecibo>
    <totalRecibo>297.25</totalRecibo>
  </Recibo>
  <Recibo idRecibo="59">
    <Exencion>N</Exencion>
    <idFilaExcel>343</idFilaExcel>
    <nombre>Pasado</nombre>
    <primerApellido>Alencar</primerApellido>
    <segundoApellido>Guerra</segundoApellido>
    <NIF>71258335B</NIF>
    <IBAN>GR4036521452776500611111</IBAN>
    <kgGenerados>76</kgGenerados>
    <baseImponibleRecibo>100.58</baseImponibleRecibo>
    <ivaRecibo>15.61</ivaRecibo>
    <totalRecibo>116.19</totalRecibo>
  </Recibo>
  <Recibo idRecibo="60">
    <Exencion>N</Exencion>
    <idFilaExcel>349</idFilaExcel>
    <nombre>Puerto</nombre>
    <primerApellido>Adolfo</primerApellido>
    <segundoApellido>Márquez</segundoApellido>
    <NIF>71258395W</NIF>
    <IBAN>ES3420960043013000111111</IBAN>
    <kgGenerados>27</kgGenerados>
    <baseImponibleRecibo>80.2</baseImponibleRecibo>
    <ivaRecibo>10.13</ivaRecibo>
    <totalRecibo>90.33</totalRecibo>
  </Recibo>
  <Recibo idRecibo="61">
    <Exencion>N</Exencion>
    <idFilaExcel>350</idFilaExcel>
    <nombre>Morán</nombre>
    <primerApellido>Giovani</primerApellido>
    <segundoApellido>Martinez</segundoApellido>
    <NIF>71258405N</NIF>
    <IBAN>GB3136585214270025411111</IBAN>
    <kgGenerados>167</kgGenerados>
    <baseImponibleRecibo>234.2</baseImponibleRecibo>
    <ivaRecibo>40.65</ivaRecibo>
    <totalRecibo>274.85</totalRecibo>
  </Recibo>
  <Recibo idRecibo="62">
    <Exencion>N</Exencion>
    <idFilaExcel>351</idFilaExcel>
    <nombre>López</nombre>
    <primerApellido>Agustín</primerApellido>
    <segundoApellido>Martínez</segundoApellido>
    <NIF>71258415E</NIF>
    <IBAN>ES1712548523455214511111</IBAN>
    <kgGenerados>82</kgGenerados>
    <baseImponibleRecibo>105.53</baseImponibleRecibo>
    <ivaRecibo>16.58</ivaRecibo>
    <totalRecibo>122.11</totalRecibo>
  </Recibo>
  <Recibo idRecibo="63">
    <Exencion>N</Exencion>
    <idFilaExcel>352</idFilaExcel>
    <nombre>Domingo</nombre>
    <primerApellido>Luis</primerApellido>
    <segundoApellido>Melcón</segundoApellido>
    <NIF>71258425D</NIF>
    <IBAN>ES0631624561072546911100</IBAN>
    <kgGenerados>122</kgGenerados>
    <baseImponibleRecibo>184.7</baseImponibleRecibo>
    <ivaRecibo>30.84</ivaRecibo>
    <totalRecibo>215.54</totalRecibo>
  </Recibo>
  <Recibo idRecibo="64">
    <Exencion>N</Exencion>
    <idFilaExcel>353</idFilaExcel>
    <nombre>Domínguez</nombre>
    <primerApellido>Armando</primerApellido>
    <segundoApellido />
    <NIF>71258435L</NIF>
    <IBAN>ES2236154231742500311111</IBAN>
    <kgGenerados>92</kgGenerados>
    <baseImponibleRecibo>151.7</baseImponibleRecibo>
    <ivaRecibo>24.3</ivaRecibo>
    <totalRecibo>176.0</totalRecibo>
  </Recibo>
  <Recibo idRecibo="65">
    <Exencion>N</Exencion>
    <idFilaExcel>354</idFilaExcel>
    <nombre>Ramos</nombre>
    <primerApellido>Latifa</primerApellido>
    <segundoApellido />
    <NIF>71258445Y</NIF>
    <IBAN>ES8244875664137231611111</IBAN>
    <kgGenerados>28</kgGenerados>
    <baseImponibleRecibo>81.3</baseImponibleRecibo>
    <ivaRecibo>10.34</ivaRecibo>
    <totalRecibo>91.64</totalRecibo>
  </Recibo>
  <Recibo idRecibo="66">
    <Exencion>N</Exencion>
    <idFilaExcel>355</idFilaExcel>
    <nombre>Cadenas</nombre>
    <primerApellido>Latifa Epfouad Erre</primerApellido>
    <segundoApellido />
    <NIF>71258455Q</NIF>
    <IBAN>ES3320960031422124811111</IBAN>
    <kgGenerados>6</kgGenerados>
    <baseImponibleRecibo>61.5</baseImponibleRecibo>
    <ivaRecibo>6.42</ivaRecibo>
    <totalRecibo>67.92</totalRecibo>
  </Recibo>
  <Recibo idRecibo="67">
    <Exencion>N</Exencion>
    <idFilaExcel>356</idFilaExcel>
    <nombre>Blanco</nombre>
    <primerApellido>Saaida</primerApellido>
    <segundoApellido>García</segundoApellido>
    <NIF>71258465A</NIF>
    <IBAN>ES5733620012907852111111</IBAN>
    <kgGenerados>200</kgGenerados>
    <baseImponibleRecibo>270.5</baseImponibleRecibo>
    <ivaRecibo>47.84</ivaRecibo>
    <totalRecibo>318.34</totalRecibo>
  </Recibo>
  <Recibo idRecibo="68">
    <Exencion>N</Exencion>
    <idFilaExcel>357</idFilaExcel>
    <nombre>Fernandez</nombre>
    <primerApellido>Antonio</primerApellido>
    <segundoApellido>García</segundoApellido>
    <NIF>71258475J</NIF>
    <IBAN>ES6133218885431445111100</IBAN>
    <kgGenerados>23</kgGenerados>
    <baseImponibleRecibo>75.8</baseImponibleRecibo>
    <ivaRecibo>9.25</ivaRecibo>
    <totalRecibo>85.05</totalRecibo>
  </Recibo>
  <Recibo idRecibo="69">
    <Exencion>N</Exencion>
    <idFilaExcel>358</idFilaExcel>
    <nombre>García</nombre>
    <primerApellido>Dorina</primerApellido>
    <segundoApellido>Getino</segundoApellido>
    <NIF>71258485T</NIF>
    <IBAN>ES2962581542723690011111</IBAN>
    <kgGenerados>183</kgGenerados>
    <baseImponibleRecibo>188.85</baseImponibleRecibo>
    <ivaRecibo>33.1</ivaRecibo>
    <totalRecibo>221.95</totalRecibo>
  </Recibo>
  <Recibo idRecibo="70">
    <Exencion>N</Exencion>
    <idFilaExcel>359</idFilaExcel>
    <nombre>Otero</nombre>
    <primerApellido>Rocío</primerApellido>
    <segundoApellido>Gomara</segundoApellido>
    <NIF>71258495X</NIF>
    <IBAN>ES2625165151118666311111</IBAN>
    <kgGenerados>73</kgGenerados>
    <baseImponibleRecibo>130.8</baseImponibleRecibo>
    <ivaRecibo>20.15</ivaRecibo>
    <totalRecibo>150.95</totalRecibo>
  </Recibo>
  <Recibo idRecibo="71">
    <Exencion>N</Exencion>
    <idFilaExcel>360</idFilaExcel>
    <nombre>Otero</nombre>
    <primerApellido>Soledad</primerApellido>
    <segundoApellido>González</segundoApellido>
    <NIF>71258505C</NIF>
    <IBAN>ES3420960043013000111111</IBAN>
    <kgGenerados>180</kgGenerados>
    <baseImponibleRecibo>248.5</baseImponibleRecibo>
    <ivaRecibo>43.48</ivaRecibo>
    <totalRecibo>291.98</totalRecibo>
  </Recibo>
  <Recibo idRecibo="72">
    <Exencion>N</Exencion>
    <idFilaExcel>361</idFilaExcel>
    <nombre>Vara</nombre>
    <primerApellido>Vittorio</primerApellido>
    <segundoApellido>González</segundoApellido>
    <NIF>71258515F</NIF>
    <IBAN>PT2336952365080014411111</IBAN>
    <kgGenerados>187</kgGenerados>
    <baseImponibleRecibo>256.2</baseImponibleRecibo>
    <ivaRecibo>45.01</ivaRecibo>
    <totalRecibo>301.21</totalRecibo>
  </Recibo>
  <Recibo idRecibo="73">
    <Exencion>N</Exencion>
    <idFilaExcel>362</idFilaExcel>
    <nombre>Martínes</nombre>
    <primerApellido>Vittorio</primerApellido>
    <segundoApellido>Gracia</segundoApellido>
    <NIF>71258525V</NIF>
    <IBAN>ES8465168874671561511111</IBAN>
    <kgGenerados>18</kgGenerados>
    <baseImponibleRecibo>70.3</baseImponibleRecibo>
    <ivaRecibo>8.16</ivaRecibo>
    <totalRecibo>78.46</totalRecibo>
  </Recibo>
  <Recibo idRecibo="74">
    <Exencion>N</Exencion>
    <idFilaExcel>363</idFilaExcel>
    <nombre>Bernal</nombre>
    <primerApellido>Mario</primerApellido>
    <segundoApellido>Guerra</segundoApellido>
    <NIF>71258535G</NIF>
    <IBAN>ES8920960583811234511100</IBAN>
    <kgGenerados>109</kgGenerados>
    <baseImponibleRecibo>127.8</baseImponibleRecibo>
    <ivaRecibo>21.0</ivaRecibo>
    <totalRecibo>148.8</totalRecibo>
  </Recibo>
  <Recibo idRecibo="75">
    <Exencion>N</Exencion>
    <idFilaExcel>364</idFilaExcel>
    <nombre>Blanco</nombre>
    <primerApellido>Concepción</primerApellido>
    <segundoApellido>Gutierrez</segundoApellido>
    <NIF>71258545Z</NIF>
    <IBAN>ES2521416325851510011111</IBAN>
    <kgGenerados>12</kgGenerados>
    <baseImponibleRecibo>63.7</baseImponibleRecibo>
    <ivaRecibo>6.86</ivaRecibo>
    <totalRecibo>70.56</totalRecibo>
  </Recibo>
  <Recibo idRecibo="76">
    <Exencion>N</Exencion>
    <idFilaExcel>365</idFilaExcel>
    <nombre>Sutil</nombre>
    <primerApellido>María</primerApellido>
    <segundoApellido>Herreras</segundoApellido>
    <NIF>71258555R</NIF>
    <IBAN>LU4632628484594115111111</IBAN>
    <kgGenerados>174</kgGenerados>
    <baseImponibleRecibo>241.9</baseImponibleRecibo>
    <ivaRecibo>42.17</ivaRecibo>
    <totalRecibo>284.07</totalRecibo>
  </Recibo>
</Recibos>
